FedxD/Lists.py
FedxD/__init__.py
FedxD/color.py
FedxD/converters.py
FedxD/discord.py
FedxD/excel.py
FedxD/pygame.py
FedxD/random.py
FedxD/shapes.py
FedxD-1.4.dist-info/License.txt
FedxD-1.4.dist-info/METADATA
FedxD-1.4.dist-info/WHEEL
FedxD-1.4.dist-info/top_level.txt
FedxD-1.4.dist-info/RECORD
