Metadata-Version: 2.1
Name: FedxD
Version: 1.4
Summary: This Package is for Quality of life stuff that you will need in your project
Home-page: https://github.com/FedxD
Author: FedxD
Author-email: abbaskazim135@gmail.com
License: MIT
Classifier: Programming Language :: Python :: 3
Classifier: License :: OSI Approved :: MIT License
Classifier: Operating System :: OS Independent
Requires-Python: >=3.10
License-File: License.txt
Requires-Dist: openpyxl
Requires-Dist: discord
Requires-Dist: pygame
